{
  "good": [
    { "name": "맛집" },
    { "name": "친절해요" },
    { "name": "인기" },
    { "name": "웨이팅" },
    { "name": "예약필수" },
    { "name": "사진맛집" },
    { "name": "데이트" },
    { "name": "이색데이트" },
    { "name": "필수코스" },
    { "name": "주차가능" },
    { "name": "핫플" },
    { "name": "혼술가능" },
    { "name": "혼밥가능" },
    { "name": "인싸코스" },
    { "name": "아싸코스" },
    { "name": "뷰포인트" },
    { "name": "24시운영" }
  ],
  "not_good": [
    { "name": "별로에요" },
    { "name": "더러워요" },
    { "name": "불친절" },
    { "name": "맛없어요" },
    { "name": "너무시끄러움" },
    { "name": "주차불가" }
  ]
}
